LICENSE
MANIFEST.in
README.md
setup.py
Arduino_Sketch.egg-info/PKG-INFO
Arduino_Sketch.egg-info/SOURCES.txt
Arduino_Sketch.egg-info/dependency_links.txt
Arduino_Sketch.egg-info/entry_points.txt
Arduino_Sketch.egg-info/not-zip-safe
Arduino_Sketch.egg-info/top_level.txt
arduino_sketch/Arduino.mk
arduino_sketch/__init__.py
arduino_sketch/app.py
arduino_sketch/ard-parse-boards
arduino_sketch/defaults_darwin.ini
arduino_sketch/defaults_other.ini
arduino_sketch.egg-info/SOURCES.txt