Metadata-Version: 1.0
Name: arduino-sketch
Version: 0.1
Summary: Compile and upload Arduino sketches from command line
Home-page: UNKNOWN
Author: Oliver Tonnhofer
Author-email: olt@bogosoft.com
License: MIT License
Keywords: arduino
Platform: UNKNOWN
Classifier: Development Status :: 4 - Beta
Classifier: Environment :: Console
Classifier: License :: OSI Approved :: MIT License
Classifier: Operating System :: POSIX
Classifier: Programming Language :: Python :: 2.6
Classifier: Programming Language :: Python :: 2.7
Classifier: Topic :: Software Development :: Build Tools
Classifier: Topic :: Software Development :: Embedded Systems
